hopeit/azure/blob_storage/__init__.py
hopeit/azure/blob_storage/object_storage.py
hopeit/azure/blob_storage/partition.py
hopeit/azure/blob_storage/py.typed
hopeit_azure_blob_storage-0.1.0.dist-info/METADATA
hopeit_azure_blob_storage-0.1.0.dist-info/WHEEL
hopeit_azure_blob_storage-0.1.0.dist-info/top_level.txt
hopeit_azure_blob_storage-0.1.0.dist-info/RECORD
