Metadata-Version: 2.4
Name: hopeit.azure.blob-storage
Version: 0.1.0
Summary: Hopeit Engine Azure Blob Storage Toolkit
Author-email: Leo Smerling & Pablo Canto <contact@hopeit.com.ar>, Leo Smerling <contact@hopeit.com.ar>, Pablo Canto <contact@hopeit.com.ar>
License: Apache 2
Project-URL: Homepage, https://github.com/hopeit-git/hopeit.azure
Project-URL: CI: GitHub Actions, https://github.com/hopeit-git/hopeit.azure/actions?query=workflow
Project-URL: GitHub: issues, https://github.com/hopeit-git/hopeit.azure/issues
Project-URL: GitHub: repo, https://github.com/hopeit-git/hopeit.azure
Classifier: License :: OSI Approved :: Apache Software License
Classifier: Intended Audience :: Developers
Classifier: Programming Language :: Python
Classifier: Programming Language :: Python :: 3.10
Classifier: Programming Language :: Python :: 3.11
Classifier: Programming Language :: Python :: 3.12
Classifier: Programming Language :: Python :: 3.13
Classifier: Development Status :: 5 - Production/Stable
Classifier: Operating System :: POSIX :: Linux
Classifier: Operating System :: MacOS :: MacOS X
Classifier: Operating System :: Microsoft :: Windows
Classifier: Topic :: Internet :: WWW/HTTP
Classifier: Topic :: Software Development :: Libraries :: Python Modules
Classifier: Framework :: AsyncIO
Requires-Dist: azure-identity>=1.23.0
Requires-Dist: azure-storage-blob>=12.25.1
Requires-Dist: hopeit.engine>=0.27.0
